mhealthlab_client/__init__.py
mhealthlab_client/android_watch.py
mhealthlab_client/client.py
mhealthlab_client/constants.py
mhealthlab_client/har.py
mhealthlab_client/known_hosts
mhealthlab_client/mhlab.py
mhealthlab_client/tests/__init__.py
mhealthlab_client/tests/test_client.py
mhealthlab_client-0.8.11.dist-info/entry_points.txt
mhealthlab_client-0.8.11.dist-info/WHEEL
mhealthlab_client-0.8.11.dist-info/METADATA
mhealthlab_client-0.8.11.dist-info/RECORD
