Metadata-Version: 2.1
Name: mhealthlab-client
Version: 0.8.11
Summary: Client to download and decrypt data for lab projects of mhealthgroup.org
License: MIT
Author: Qu Tang
Author-email: tang.q@northeastern.edu
Requires-Python: >=3.7.0,<4.0.0
Classifier: License :: OSI Approved :: MIT License
Classifier: Programming Language :: Python :: 3
Classifier: Programming Language :: Python :: 3.7
Classifier: Programming Language :: Python :: 3.8
Requires-Dist: arus (>=1.1.18,<2.0.0)
Requires-Dist: arus-muss (>=0.2.0,<0.3.0)
Requires-Dist: outdated (>=0.2.0,<0.3.0)
Requires-Dist: pysftp (>=0.2.9,<0.3.0)
Requires-Dist: pyzipper (>=0.3.1,<0.4.0)
